pandalyse/__init__.py
pandalyse/analysis.py
pandalyse/catalogue.py
pandalyse/selector.py
pandalyse/trainings.py
pandalyse/utilities.py
pandalyse-0.1.2.dist-info/AUTHORS.rst
pandalyse-0.1.2.dist-info/LICENSE.txt
pandalyse-0.1.2.dist-info/METADATA
pandalyse-0.1.2.dist-info/WHEEL
pandalyse-0.1.2.dist-info/top_level.txt
pandalyse-0.1.2.dist-info/RECORD
