Metadata-Version: 2.1
Name: pandalyse
Version: 0.1.2
Summary: A toolkit for an analysis environment with pandas.
Home-page: https://github.com/simonUU/pandalyse
Author: Simon Wehle
Author-email: simon.wehle@desy.de
License: mit
Project-URL: Documentation, https://pandalyse.readthedocs.io/en/latest/
Platform: any
Classifier: Development Status :: 4 - Beta
Classifier: Programming Language :: Python
Provides-Extra: testing
Requires-Dist: pytest ; extra == 'testing'
Requires-Dist: pytest-cov ; extra == 'testing'
